aider_mcp_client/__init__.py
aider_mcp_client/client.py
aider_mcp_client/config.json
aider_mcp_client/get_react_docs.py
aider_mcp_client/mcp_sdk_client.py
aider_mcp_client/test_connection.py
aider_mcp_client-0.1.3.dist-info/licenses/LICENSE
aider_mcp_client-0.1.3.dist-info/METADATA
aider_mcp_client-0.1.3.dist-info/WHEEL
aider_mcp_client-0.1.3.dist-info/entry_points.txt
aider_mcp_client-0.1.3.dist-info/top_level.txt
aider_mcp_client-0.1.3.dist-info/RECORD
