Metadata-Version: 2.4
Name: aider-mcp-client
Version: 0.1.3
License-File: LICENSE
Requires-Dist: requests>=2.25.0
Dynamic: license-file
Dynamic: requires-dist
